README
setup.cfg
setup.py
pvdl/__init__.py
pvdl/pvdl.py
pvdl.egg-info/PKG-INFO
pvdl.egg-info/SOURCES.txt
pvdl.egg-info/dependency_links.txt
pvdl.egg-info/entry_points.txt
pvdl.egg-info/requires.txt
pvdl.egg-info/top_level.txt