Metadata-Version: 2.1
Name: pvdl
Version: 0.9
Summary: PacktPub Video Downloader, The Easiest way to download any Packt video tutorial using subscription
Home-page: https://github.com/TheWeirdDev/PacktPub-Video-Downloader
Download-URL: https://github.com/TheWeirdDev/PacktPub-Video-Downloader/archive/0.9.tar.gz
Author: TheWeirdDev
Author-email: alireza6677@gmail.com
License: GPL-3.0
Keywords: packt,packtpub,packtpub-downloader,packtpub-video-downloader,video-downloader,subscription,free-trial
Classifier: Development Status :: 5 - Production/Stable
Classifier: Intended Audience :: End Users/Desktop
Classifier: Topic :: Multimedia :: Video
Classifier: License :: OSI Approved :: GNU General Public License v3 or later (GPLv3+)
Classifier: Programming Language :: Python :: 3
Classifier: Programming Language :: Python :: 3.6
Classifier: Programming Language :: Python :: 3.7
Classifier: Programming Language :: Python :: 3.8
Classifier: Programming Language :: Python :: 3.9
Classifier: Programming Language :: Python :: 3.10
Classifier: Programming Language :: Python :: 3.11
Classifier: Programming Language :: Python :: 3 :: Only
